PyFlyt/__init__.py
PyFlyt/core/__init__.py
PyFlyt/core/aviary.py
PyFlyt/core/abstractions/__init__.py
PyFlyt/core/abstractions/base_controller.py
PyFlyt/core/abstractions/base_drone.py
PyFlyt/core/abstractions/base_wind_field.py
PyFlyt/core/abstractions/boosters.py
PyFlyt/core/abstractions/boring_bodies.py
PyFlyt/core/abstractions/camera.py
PyFlyt/core/abstractions/gimbals.py
PyFlyt/core/abstractions/lifting_surfaces.py
PyFlyt/core/abstractions/motors.py
PyFlyt/core/abstractions/pid.py
PyFlyt/core/drones/__init__.py
PyFlyt/core/drones/fixedwing.py
PyFlyt/core/drones/quadx.py
PyFlyt/core/drones/rocket.py
PyFlyt/core/utils/compile_helpers.py
PyFlyt/core/utils/load_objs.py
PyFlyt/core/wind/__init__.py
PyFlyt/gym_envs/__init__.py
PyFlyt/gym_envs/fixedwing_envs/fixedwing_base_env.py
PyFlyt/gym_envs/fixedwing_envs/fixedwing_waypoints_env.py
PyFlyt/gym_envs/quadx_envs/quadx_ball_in_cup_env.py
PyFlyt/gym_envs/quadx_envs/quadx_base_env.py
PyFlyt/gym_envs/quadx_envs/quadx_gates_env.py
PyFlyt/gym_envs/quadx_envs/quadx_hover_env.py
PyFlyt/gym_envs/quadx_envs/quadx_pole_balance_env.py
PyFlyt/gym_envs/quadx_envs/quadx_pole_waypoints_env.py
PyFlyt/gym_envs/quadx_envs/quadx_waypoints_env.py
PyFlyt/gym_envs/rocket_envs/rocket_base_env.py
PyFlyt/gym_envs/rocket_envs/rocket_landing_env.py
PyFlyt/gym_envs/utils/flatten_waypoint_env.py
PyFlyt/gym_envs/utils/pole_handler.py
PyFlyt/gym_envs/utils/waypoint_handler.py
PyFlyt/models/ball_and_string.urdf
PyFlyt/models/cup.urdf
PyFlyt/models/landing_pad.urdf
PyFlyt/models/pole.urdf
PyFlyt/models/race_gate.urdf
PyFlyt/models/target.urdf
PyFlyt/models/vehicles/acrowing/acrowing.urdf
PyFlyt/models/vehicles/acrowing/acrowing.yaml
PyFlyt/models/vehicles/cf2x/cf2.dae
PyFlyt/models/vehicles/cf2x/cf2x.urdf
PyFlyt/models/vehicles/cf2x/cf2x.yaml
PyFlyt/models/vehicles/fixedwing/fixedwing.urdf
PyFlyt/models/vehicles/fixedwing/fixedwing.yaml
PyFlyt/models/vehicles/primitive_drone/primitive_drone.urdf
pyflyt-0.29.0.dist-info/LICENSE.txt
pyflyt-0.29.0.dist-info/METADATA
pyflyt-0.29.0.dist-info/WHEEL
pyflyt-0.29.0.dist-info/top_level.txt
pyflyt-0.29.0.dist-info/RECORD
