Metadata-Version: 2.2
Name: PyFlyt
Version: 0.29.0
Summary: UAV Flight Simulator Gymnasium Environments for Reinforcement Learning Research.
Author-email: Jet <taijunjet@hotmail.com>
License: MIT License
Project-URL: Repository, https://github.com/jjshoots/PyFlyt
Project-URL: Documentation, https://jjshoots.github.io/PyFlyt/documentation.html
Project-URL: Bug Report, https://github.com/jjshoots/PyFlyt/issues
Keywords: Reinforcement Learning,UAVs,drones,Quadcopter,AI,RL,Gymnasium
Classifier: Programming Language :: Python :: 3
Classifier: License :: OSI Approved :: MIT License
Classifier: Operating System :: OS Independent
Requires-Python: >=3.8
License-File: LICENSE.txt
Requires-Dist: numba
Requires-Dist: numpy<2.0.0
Requires-Dist: scipy
Requires-Dist: gymnasium
Requires-Dist: pettingzoo
Requires-Dist: pybullet
Requires-Dist: pyyaml
Provides-Extra: dev
Requires-Dist: pytest; extra == "dev"
Requires-Dist: pytest-cov; extra == "dev"
Requires-Dist: codecov; extra == "dev"
Requires-Dist: pre-commit; extra == "dev"
Requires-Dist: matplotlib; extra == "dev"
